flowws_keras_geometry/__init__.py
flowws_keras_geometry/algebra.py
flowws_keras_geometry/layers.py
flowws_keras_geometry/version.py
flowws_keras_geometry/data/ImportMatProjChargeDensity.py
flowws_keras_geometry/data/ImportOCP.py
flowws_keras_geometry/data/MD17.py
flowws_keras_geometry/data/MatProjChargeDensity.py
flowws_keras_geometry/data/ModelNet.py
flowws_keras_geometry/data/PDBCache.py
flowws_keras_geometry/data/PDBCoarseGrained.py
flowws_keras_geometry/data/PyriodicDataset.py
flowws_keras_geometry/data/RMD17.py
flowws_keras_geometry/data/__init__.py
flowws_keras_geometry/data/internal.py
flowws_keras_geometry/data/keras_metrics.py
flowws_keras_geometry/models/CrystalStructureClassification.py
flowws_keras_geometry/models/GalaMoleculeForceRegression.py
flowws_keras_geometry/models/GalaPDBInverseCoarseGrain.py
flowws_keras_geometry/models/MoleculeForceRegression.py
flowws_keras_geometry/models/PDBInverseCoarseGrain.py
flowws_keras_geometry/models/PDBInverseCoarseGrainTransformer.py
flowws_keras_geometry/models/__init__.py
flowws_keras_geometry/models/internal.py
flowws_keras_geometry/viz/BackmapCoarseGrainViewer.py
flowws_keras_geometry/viz/MatProjChargeDensityViewer.py
flowws_keras_geometry/viz/MoleculeAttentionViewer.py
flowws_keras_geometry/viz/ParticleAttentionViewer.py
flowws_keras_geometry/viz/__init__.py
flowws_keras_geometry-0.5.1.dist-info/LICENSE
flowws_keras_geometry-0.5.1.dist-info/METADATA
flowws_keras_geometry-0.5.1.dist-info/WHEEL
flowws_keras_geometry-0.5.1.dist-info/entry_points.txt
flowws_keras_geometry-0.5.1.dist-info/top_level.txt
flowws_keras_geometry-0.5.1.dist-info/RECORD
