Metadata-Version: 2.1
Name: flowws-keras-geometry
Version: 0.5.1
Summary: Stage-based scientific workflows for deep learning experiments with geometric algebra
Author: Matthew Spellings
Author-email: mspells@vectorinstitute.ai
License: MIT
Classifier: Development Status :: 3 - Alpha
Classifier: License :: OSI Approved :: MIT License
Classifier: Programming Language :: Python :: 3
Requires-Python: >=3
License-File: LICENSE
Requires-Dist: flowws
Requires-Dist: flowws-keras-experimental
